gatered/__init__.py
gatered/client.py
gatered/func.py
gatered/pushshift.py
gatered/utils.py
gatered-1.3.1.dist-info/LICENSE
gatered-1.3.1.dist-info/WHEEL
gatered-1.3.1.dist-info/METADATA
gatered-1.3.1.dist-info/RECORD
