Metadata-Version: 2.1
Name: gatered
Version: 1.3.1
Summary: Reddit Gateway API Library
Home-page: https://github.com/CounterTek/gatered
License: Apache-2.0
Keywords: reddit,reddit api
Author: DaRekaze
Author-email: darekaze@gmail.com
Requires-Python: >=3.8,<4.0
Classifier: Intended Audience :: Developers
Classifier: License :: OSI Approved :: Apache Software License
Classifier: Programming Language :: Python :: 3
Classifier: Programming Language :: Python :: 3.10
Classifier: Programming Language :: Python :: 3.8
Classifier: Programming Language :: Python :: 3.9
Classifier: Programming Language :: Python :: Implementation :: CPython
Classifier: Topic :: Software Development :: Libraries :: Python Modules
Requires-Dist: aiometer (>=0.3.0)
Requires-Dist: httpx[socks,http2] (>=0.21.0)
Project-URL: Change Log, https://github.com/countertek/gatered/blob/main/CHANGELOG.md
Project-URL: Documentation, https://countertek.github.io/gatered
Project-URL: Repository, https://github.com/CounterTek/gatered
